lichv
