Metadata-Version: 1.2
Name: lichv
Version: 0.0.29
Summary: Utility tools with mysqldb,postgresql,utils
Home-page: https://github.com/lichv/python
Author: lichv
Author-email: lichvy@126.com
License: UNKNOWN
Platform: UNKNOWN
Requires-Python: >=3.6
